LICENSE
README.md
setup.py
honeycheck/__init__.py
honeycheck/__main__.py
honeycheck/app_preparation.py
honeycheck/dhcp_watchmen.py
honeycheck.egg-info/PKG-INFO
honeycheck.egg-info/SOURCES.txt
honeycheck.egg-info/dependency_links.txt
honeycheck.egg-info/requires.txt
honeycheck.egg-info/top_level.txt
honeycheck/modules/__init__.py
honeycheck/modules/base_control.py
honeycheck/modules/script.py
honeycheck/tests/__init__.py
honeycheck/tests/test_conf_checks.py