Metadata-Version: 2.1
Name: honeycheck
Version: 0.2.1
Summary: Honeycheck detects rogue dhcp servers and provides a modular and fully configurable action environment in case they are found
Home-page: https://github.com/elchicodepython/HoneyCheck
Author: Samuel López Saura
Author-email: samuellopezsaura@gmail.com
License: MIT
Platform: UNKNOWN
Classifier: Programming Language :: Python :: 3
Classifier: License :: OSI Approved :: MIT License
Classifier: Operating System :: OS Independent
License-File: LICENSE
